MajorProblem/__init__.py
MajorProblem/pushshift.py
MajorProblem_bot_zachicecreamcohn-0.0.1.dist-info/LICENSE
MajorProblem_bot_zachicecreamcohn-0.0.1.dist-info/METADATA
MajorProblem_bot_zachicecreamcohn-0.0.1.dist-info/WHEEL
MajorProblem_bot_zachicecreamcohn-0.0.1.dist-info/top_level.txt
MajorProblem_bot_zachicecreamcohn-0.0.1.dist-info/RECORD
