Metadata-Version: 2.1
Name: MajorProblem_bot-zachicecreamcohn
Version: 0.0.1
Summary: a simple Reddit bot that finds comments that mention a major problem and respond: MAJOR PROBLEM!
Home-page: https://github.com/zachicecreamcohn/MajorProblem_bot
Author: Zach Cohn
Author-email: mypythonexperiments@gmail.com
License: UNKNOWN
Project-URL: Bug Tracker, https://github.com/zachicecreamcohn/MajorProblem_bot/issues
Platform: UNKNOWN
Classifier: Programming Language :: Python :: 3
Classifier: License :: OSI Approved :: MIT License
Requires-Python: >=3.9
License-File: LICENSE
